core_pagination/__init__.py
core_pagination/pagination_dtos.py
core_pagination/pagination_mappers.py
core_pagination/pagination_tos.py
core_pagination/pagination_types.py
core_pagination/py.typed
turintech_pagination-2.0.0.dist-info/METADATA
turintech_pagination-2.0.0.dist-info/WHEEL
turintech_pagination-2.0.0.dist-info/licenses/LICENSE
turintech_pagination-2.0.0.dist-info/RECORD
